bootstrap.py
buildout.cfg
changes.txt
setup.py
alchemist/__init__.py
alchemist.traversal.egg-info/PKG-INFO
alchemist.traversal.egg-info/SOURCES.txt
alchemist.traversal.egg-info/dependency_links.txt
alchemist.traversal.egg-info/namespace_packages.txt
alchemist.traversal.egg-info/not-zip-safe
alchemist.traversal.egg-info/requires.txt
alchemist.traversal.egg-info/top_level.txt
alchemist/traversal/__init__.py
alchemist/traversal/collection.py
alchemist/traversal/configure.zcml
alchemist/traversal/interfaces.py
alchemist/traversal/managed.py
alchemist/traversal/managed.txt
alchemist/traversal/readme.txt
alchemist/traversal/tests.py