Metadata-Version: 1.0
Name: alchemist.traversal
Version: 0.4.0
Summary: Foreign Key Traversal mechanisms for alchemist containers and domain objects.
Home-page: UNKNOWN
Author: Kapil Thangavelu
Author-email: kapil.foss@gmail.com
License: LGPL
Keywords: zope zope3
Platform: UNKNOWN
Classifier: Framework :: Zope3
